pyvichan/__init__.py
pyvichan/board.py
pyvichan/file.py
pyvichan/post.py
pyvichan/thread.py
pyvichan/url.py
pyvichan/util.py
pyvichan-0.4.4.dist-info/LICENSE
pyvichan-0.4.4.dist-info/METADATA
pyvichan-0.4.4.dist-info/WHEEL
pyvichan-0.4.4.dist-info/top_level.txt
pyvichan-0.4.4.dist-info/RECORD
