Metadata-Version: 2.1
Name: pyvichan
Version: 0.4.4
Summary: Python vichan API Wrapper. Based on BASC-py4chan by the Bibliotheca Anonoma
Home-page: http://github.com/bibanon/pyvichan
Author: Antonizoon Overtwater
Author-email: antonizoon@bibanon.org
License: DO WHAT THE FUCK YOU WANT TO PUBLIC LICENSE
Keywords: 8chan api vichan
Classifier: Intended Audience :: Developers
Classifier: Natural Language :: English
Classifier: Programming Language :: Python :: 2
Classifier: Programming Language :: Python :: 3
License-File: LICENSE
Requires-Dist: requests (>=1.0.0)
